dmu_tools/__init__.py
dmu_tools/aic.py
dmu_tools/data_filter.py
dmu_tools/data_generator.py
dmu_tools/dmu.py
dmu_tools/draw_heritability.py
dmu_tools/tools.py
dmu_tools-0.0.5.dist-info/METADATA
dmu_tools-0.0.5.dist-info/WHEEL
dmu_tools-0.0.5.dist-info/licenses/LICENSE
dmu_tools-0.0.5.dist-info/RECORD
